setup.py
byrlogin/__init__.py
byrlogin/byrlogin.py
byrlogin.egg-info/PKG-INFO
byrlogin.egg-info/SOURCES.txt
byrlogin.egg-info/dependency_links.txt
byrlogin.egg-info/entry_points.txt
byrlogin.egg-info/not-zip-safe
byrlogin.egg-info/pbr.json
byrlogin.egg-info/requires.txt
byrlogin.egg-info/top_level.txt