Metadata-Version: 1.0
Name: byrlogin
Version: 1.1.0
Summary: 北邮人登录网关脚本
Home-page: https://github.com/wzyuliyang/byrlogin
Author: wzyuliyang
Author-email: wzyuliyang911@gmail.com
License: MIT License
Keywords: python byrlogin
Platform: UNKNOWN
